{
  "info": {
    "_postman_id": "caf4fab8-a117-41ab-8d87-5ad45ea1b9ea",
    "name": "kasir-pure-go",
    "schema": "https://schema.getpostman.com/json/collection/v2.1.0/collection.json"
  },
  "item": [
    {
      "name": "category",
      "item": [
        {
          "name": "Create",
          "id": "e2946ddd-48bc-4553-9d4b-4c9bc2e7e106",
          "request": {
            "auth": {
              "type": "noauth"
            },
            "method": "POST",
            "header": [],
            "body": {
              "mode": "raw",
              "raw": "{\n    \"name\":\"sabun\",\n    \"description\":\"rumah tangga\"\n}",
              "options": {
                "raw": {
                  "language": "json"
                }
              }
            },
            "url": {
              "raw": "{{host}}/api/categories",
              "host": [
                "{{host}}"
              ],
              "path": [
                "api",
                "categories"
              ]
            }
          },
          "response": []
        },
        {
          "name": "Update",
          "id": "ee46c80c-aed0-4502-9829-2e3fb78538df",
          "request": {
            "auth": {
              "type": "noauth"
            },
            "method": "PUT",
            "header": [],
            "body": {
              "mode": "raw",
              "raw": "{\n    \"name\":\"basoka\",\n    \"description\":\"senjata\"\n}",
              "options": {
                "raw": {
                  "language": "json"
                }
              }
            },
            "url": {
              "raw": "{{host}}/api/categories/1",
              "host": [
                "{{host}}"
              ],
              "path": [
                "api",
                "categories",
                "1"
              ]
            }
          },
          "response": []
        },
        {
          "name": "GetAll",
          "id": "c56eea4b-9e7d-4e93-9082-c0e0a1f1a2ce",
          "request": {
            "auth": {
              "type": "noauth"
            },
            "method": "GET",
            "header": [],
            "url": {
              "raw": "{{host}}/api/categories",
              "host": [
                "{{host}}"
              ],
              "path": [
                "api",
                "categories"
              ]
            }
          },
          "response": []
        },
        {
          "name": "Delete",
          "id": "49bae77f-7743-442b-9811-fd1c66328ca9",
          "request": {
            "method": "DELETE",
            "header": [],
            "url": {
              "raw": "{{host}}/api/categories/1",
              "host": [
                "{{host}}"
              ],
              "path": [
                "api",
                "categories",
                "1"
              ]
            }
          },
          "response": []
        }
      ],
      "id": "67918658-3108-4e04-897d-71cc8e6371b6"
    },
    {
      "name": "product",
      "item": [
        {
          "name": "Create",
          "id": "962642c1-03dc-4df8-8929-5ecc13f078f4",
          "request": {
            "auth": {
              "type": "noauth"
            },
            "method": "POST",
            "header": [],
            "body": {
              "mode": "raw",
              "raw": "{\n    \"name\":\"rinso\",\n    \"price\":1200,\n    \"stock\":12,\n    \"category_id\":2\n}",
              "options": {
                "raw": {
                  "language": "json"
                }
              }
            },
            "url": {
              "raw": "{{host}}/api/produk",
              "host": [
                "{{host}}"
              ],
              "path": [
                "api",
                "produk"
              ]
            }
          },
          "response": []
        },
        {
          "name": "Update",
          "id": "1ea0c065-c397-4ebc-955c-7aeda17a91d5",
          "request": {
            "auth": {
              "type": "noauth"
            },
            "method": "PUT",
            "header": [],
            "body": {
              "mode": "raw",
              "raw": "{\n    \"name\":\"basoka\",\n    \"description\":\"senjata\"\n}",
              "options": {
                "raw": {
                  "language": "json"
                }
              }
            },
            "url": {
              "raw": "{{host}}api/categories/1",
              "host": [
                "{{host}}api"
              ],
              "path": [
                "categories",
                "1"
              ]
            }
          },
          "response": []
        },
        {
          "name": "GetAll",
          "id": "65c5618e-5263-429b-8cc1-fb876c84c328",
          "request": {
            "auth": {
              "type": "noauth"
            },
            "method": "GET",
            "header": [],
            "url": {
              "raw": "{{host}}/api/produk",
              "host": [
                "{{host}}"
              ],
              "path": [
                "api",
                "produk"
              ]
            }
          },
          "response": []
        },
        {
          "name": "Delete",
          "id": "a5d31199-c4bb-4433-82fd-6f09a012a6db",
          "request": {
            "method": "DELETE",
            "header": [],
            "url": {
              "raw": "{{host}}/api/categories/1",
              "host": [
                "{{host}}"
              ],
              "path": [
                "api",
                "categories",
                "1"
              ]
            }
          },
          "response": []
        }
      ],
      "id": "057973aa-9396-4c97-9c98-169216a9cd06"
    }
  ],
  "variable": [
    {
      "id": "f44af12b-34a6-4e3d-b742-3bca3826c74d",
      "key": "host",
      "value": "",
      "type": "default"
    }
  ]
}